twitch_ws_irc/__init__.py
twitch_ws_irc/client.py
twitch_ws_irc/events.py
twitch_ws_irc/irc_visitor.py
twitch_ws_irc/antlr/__init__.py
twitch_ws_irc/antlr/irc/IRCLexer.py
twitch_ws_irc/antlr/irc/IRCListener.py
twitch_ws_irc/antlr/irc/IRCParser.py
twitch_ws_irc/antlr/irc/IRCVisitor.py
twitch_ws_irc/antlr/irc/__init__.py
twitch_ws_irc-0.0.7.dist-info/LICENSE
twitch_ws_irc-0.0.7.dist-info/METADATA
twitch_ws_irc-0.0.7.dist-info/WHEEL
twitch_ws_irc-0.0.7.dist-info/top_level.txt
twitch_ws_irc-0.0.7.dist-info/RECORD
