Metadata-Version: 2.1
Name: twitch-ws-irc
Version: 0.0.7
Summary: A websocket based twitch irc chat client
Home-page: https://gitlab.com/henny022/twitch-ws-irc
Author: Henny022
Author-email: hen.geheim22@gmail.com
License: MIT License
Platform: UNKNOWN
Classifier: Framework :: Django
Classifier: License :: OSI Approved :: MIT License
Classifier: Programming Language :: Python :: 3
Classifier: Programming Language :: Python :: 3.5
Requires-Python: >=3.7
License-File: LICENSE
Requires-Dist: antlr4-python3-runtime (==4.7.1)
Requires-Dist: websockets
